{
  "api": {
    "quotegen": {
      "dependsOn": [],
      "output": {
        "authConfig": {
          "additionalAuthenticationProviders": [],
          "defaultAuthentication": {
            "authenticationType": "AWS_IAM"
          }
        }
      },
      "providerPlugin": "awscloudformation",
      "service": "AppSync"
    }
  },
  "auth": {
    "quotegen6d393507": {
      "customAuth": false,
      "dependsOn": [],
      "frontendAuthConfig": {
        "mfaConfiguration": "OFF",
        "mfaTypes": [
          "SMS"
        ],
        "passwordProtectionSettings": {
          "passwordPolicyCharacters": [],
          "passwordPolicyMinLength": 8
        },
        "signupAttributes": [
          "EMAIL"
        ],
        "socialProviders": [],
        "usernameAttributes": [],
        "verificationMechanisms": [
          "EMAIL"
        ]
      },
      "providerPlugin": "awscloudformation",
      "service": "Cognito"
    }
  },
  "function": {
    "quotegenLambda": {
      "build": true,
      "providerPlugin": "awscloudformation",
      "service": "Lambda"
    }
  },
  "parameters": {
    "AMPLIFY_function_quotegenLambda_deploymentBucketName": {
      "usedBy": [
        {
          "category": "function",
          "resourceName": "quotegenLambda"
        }
      ]
    },
    "AMPLIFY_function_quotegenLambda_s3Key": {
      "usedBy": [
        {
          "category": "function",
          "resourceName": "quotegenLambda"
        }
      ]
    }
  }
}